README.md
setup.cfg
setup.py
rlog_async/__init__.py
rlog_async/_compat.py
rlog_async/formatters.py
rlog_async/handlers.py
rlog_async.egg-info/PKG-INFO
rlog_async.egg-info/SOURCES.txt
rlog_async.egg-info/dependency_links.txt
rlog_async.egg-info/not-zip-safe
rlog_async.egg-info/requires.txt
rlog_async.egg-info/top_level.txt
tests/__init__.py
tests/_compat.py
tests/conftest.py
tests/test_formatters.py
tests/test_handlers.py