Metadata-Version: 2.1
Name: rlog-async
Version: 0.0.3
Summary: Small handler and formatter for using python logging with Redis
Home-page: https://github.com/Serhg94/rlog_async
License: MIT
Keywords: Redis,logging,log,logs
Platform: UNKNOWN
Classifier: License :: OSI Approved :: MIT License
Classifier: Programming Language :: Python :: 2.6
Classifier: Programming Language :: Python :: 2.7
Classifier: Programming Language :: Python :: 3
Classifier: Programming Language :: Python :: 3.5
Classifier: Programming Language :: Python :: 3.6
Classifier: Topic :: Text Processing :: Linguistic
